acp_plugin_gamesdk/acp_plugin.py
acp_plugin_gamesdk/env.py
acp_plugin_gamesdk/interface.py
acp_plugin_gamesdk-0.2.8.dist-info/METADATA
acp_plugin_gamesdk-0.2.8.dist-info/WHEEL
acp_plugin_gamesdk-0.2.8.dist-info/RECORD
