Metadata-Version: 2.3
Name: acp-plugin-gamesdk
Version: 0.2.8
Summary: ACP Plugin for Python SDK for GAME by Virtuals
Author: Steven Lee Soon Fatt
Author-email: steven@virtuals.io
Requires-Python: >=3.10,<3.13
Classifier: Programming Language :: Python :: 3
Classifier: Programming Language :: Python :: 3.10
Classifier: Programming Language :: Python :: 3.11
Classifier: Programming Language :: Python :: 3.12
Requires-Dist: dacite (>=1.9.2,<2.0.0)
Requires-Dist: game-sdk (>=0.1.5)
Requires-Dist: python-dotenv (>=1.1.0,<2.0.0)
Requires-Dist: rich (>=13.9.4,<15.0.0)
Requires-Dist: twitter-plugin-gamesdk (>=0.2.10,<0.3.0)
Requires-Dist: virtuals-acp (>=0.2.6,<0.3.0)
